audiolm_superfeel/__init__.py
audiolm_superfeel/attend.py
audiolm_superfeel/audiolm_superfeel.py
audiolm_superfeel/data.py
audiolm_superfeel/encodec.py
audiolm_superfeel/hubert_kmeans.py
audiolm_superfeel/optimizer.py
audiolm_superfeel/soundstream.py
audiolm_superfeel/t5.py
audiolm_superfeel/trainer.py
audiolm_superfeel/utils.py
audiolm_superfeel/version.py
audiolm_superfeel/vq_wav2vec.py
audiolm_superfeel-2.1.7.dist-info/LICENSE
audiolm_superfeel-2.1.7.dist-info/METADATA
audiolm_superfeel-2.1.7.dist-info/WHEEL
audiolm_superfeel-2.1.7.dist-info/top_level.txt
audiolm_superfeel-2.1.7.dist-info/RECORD
