Metadata-Version: 2.1
Name: audiolm-superfeel
Version: 2.1.7
Summary: AudioLM - Language Modeling Approach to Audio Generation from Google Research - Pytorch
Home-page: https://github.com/osehmathias/audiolm-superfeel
Author: Phil Wang & Oseh Mathias
Author-email: o@matmail.me
License: MIT
Keywords: artificial intelligence,deep learning,transformers,attention mechanism,audio generation
Classifier: Development Status :: 4 - Beta
Classifier: Intended Audience :: Developers
Classifier: Topic :: Scientific/Engineering :: Artificial Intelligence
Classifier: License :: OSI Approved :: MIT License
Classifier: Programming Language :: Python :: 3.6
License-File: LICENSE
Requires-Dist: accelerate >=0.24.0
Requires-Dist: beartype >=0.16.1
Requires-Dist: einops >=0.7.0
Requires-Dist: ema-pytorch >=0.2.2
Requires-Dist: encodec
Requires-Dist: fairseq
Requires-Dist: wandb
Requires-Dist: gateloop-transformer >=0.2.3
Requires-Dist: joblib
Requires-Dist: local-attention >=1.9.0
Requires-Dist: pytorch-warmup
Requires-Dist: scikit-learn
Requires-Dist: sentencepiece
Requires-Dist: torch >=2.1
Requires-Dist: torchaudio
Requires-Dist: transformers
Requires-Dist: tqdm
Requires-Dist: vector-quantize-pytorch >=1.12.5
